{
    "@id": "http://cnschema.org/jobTitle", 
    "_group_property": true, 
    "_layer": "core", 
    "_node_label": "jobTitle", 
    "_paths": [
        {
            "_last": true, 
            "_path": [
                {
                    "@id": "http://cnschema.org/Thing", 
                    "rdfs:label": "Thing"
                }, 
                {
                    "@id": "http://meta.cnschema.org/Property", 
                    "rdfs:label": "Property"
                }, 
                {
                    "@id": "http://cnschema.org/jobTitle", 
                    "_lastone": true, 
                    "rdfs:label": "jobTitle"
                }
            ]
        }
    ], 
    "_sitename": "cnschema.org", 
    "_url_root": ".", 
    "_url_schema": "http://cnschema.org", 
    "_usage": "Between 100,000 and 250,000 domains", 
    "_version": "3.4", 
    "descriptionZh": "一个人的工作头衔", 
    "domainIncludes": [
        {
            "@id": "http://cnschema.org/Person", 
            "_last": true, 
            "rdfs:label": "Person"
        }
    ], 
    "nameZh": "工作头衔", 
    "rangeIncludes": [
        {
            "@id": "http://cnschema.org/Text", 
            "_last": true, 
            "rdfs:label": "Text"
        }
    ], 
    "rdfs:comment": "The job title of the person (for example, Financial Manager).", 
    "rdfs:label": "jobTitle", 
    "wikidataName": "", 
    "wikidataUrl": "", 
    "wikipediaUrl": ""
}