{
    "@id": "http://cnschema.org/keywords", 
    "_group_property": true, 
    "_layer": "core", 
    "_node_label": "keywords", 
    "_paths": [
        {
            "_last": true, 
            "_path": [
                {
                    "@id": "http://cnschema.org/Thing", 
                    "rdfs:label": "Thing"
                }, 
                {
                    "@id": "http://meta.cnschema.org/Property", 
                    "rdfs:label": "Property"
                }, 
                {
                    "@id": "http://cnschema.org/keywords", 
                    "_lastone": true, 
                    "rdfs:label": "keywords"
                }
            ]
        }
    ], 
    "_sitename": "cnschema.org", 
    "_url_root": ".", 
    "_url_schema": "http://cnschema.org", 
    "_usage": "Between 250,000 and 500,000 domains", 
    "_version": "3.4", 
    "descriptionZh": "文章中的关键词或标签", 
    "domainIncludes": [
        {
            "@id": "http://cnschema.org/CreativeWork", 
            "_last": true, 
            "rdfs:label": "CreativeWork"
        }
    ], 
    "nameZh": "关键词", 
    "rangeIncludes": [
        {
            "@id": "http://cnschema.org/Text", 
            "_last": true, 
            "rdfs:label": "Text"
        }
    ], 
    "rdfs:comment": "Keywords or tags used to describe this content. Multiple entries in a keywords list are typically delimited by commas.", 
    "rdfs:label": "keywords", 
    "wikidataName": "", 
    "wikidataUrl": "", 
    "wikipediaUrl": ""
}