{
    "@id": "http://cnschema.org/members", 
    "_group_property": true, 
    "_layer": "core", 
    "_node_label": "members", 
    "_paths": [
        {
            "_last": true, 
            "_path": [
                {
                    "@id": "http://cnschema.org/Thing", 
                    "rdfs:label": "Thing"
                }, 
                {
                    "@id": "http://meta.cnschema.org/Property", 
                    "rdfs:label": "Property"
                }, 
                {
                    "@id": "http://cnschema.org/members", 
                    "_lastone": true, 
                    "rdfs:label": "members"
                }
            ]
        }
    ], 
    "_sitename": "cnschema.org", 
    "_url_root": ".", 
    "_url_schema": "http://cnschema.org", 
    "_usage": "Between 100 and 1000 domains", 
    "_version": "3.4", 
    "descriptionZh": "组织的会员", 
    "domainIncludes": [
        {
            "@id": "http://cnschema.org/Organization", 
            "rdfs:label": "Organization"
        }, 
        {
            "@id": "http://cnschema.org/ProgramMembership", 
            "_last": true, 
            "rdfs:label": "ProgramMembership"
        }
    ], 
    "nameZh": "会员", 
    "rangeIncludes": [
        {
            "@id": "http://cnschema.org/Organization", 
            "rdfs:label": "Organization"
        }, 
        {
            "@id": "http://cnschema.org/Person", 
            "_last": true, 
            "rdfs:label": "Person"
        }
    ], 
    "rdfs:comment": "A member of this organization.", 
    "rdfs:label": "members", 
    "supersededBy": {
        "@id": "http://cnschema.org/member", 
        "rdfs:label": "member"
    }, 
    "wikidataName": "", 
    "wikidataUrl": "", 
    "wikipediaUrl": "https://en.wikipedia.org/wiki/Members"
}