{
    "@id": "http://cnschema.org/vehicleSpecialUsage", 
    "_group_property": true, 
    "_layer": "core", 
    "_node_label": "vehicleSpecialUsage", 
    "_paths": [
        {
            "_last": true, 
            "_path": [
                {
                    "@id": "http://cnschema.org/Thing", 
                    "rdfs:label": "Thing"
                }, 
                {
                    "@id": "http://meta.cnschema.org/Property", 
                    "rdfs:label": "Property"
                }, 
                {
                    "@id": "http://cnschema.org/vehicleSpecialUsage", 
                    "_lastone": true, 
                    "rdfs:label": "vehicleSpecialUsage"
                }
            ]
        }
    ], 
    "_sitename": "cnschema.org", 
    "_url_root": ".", 
    "_url_schema": "http://cnschema.org", 
    "_usage": "", 
    "_version": "3.4", 
    "descriptionZh": "指示车辆是否用于特殊用途，如商业租赁，驾驶学校或出租车。 许多国家的立法要求在出售汽车时披露这些资料。", 
    "domainIncludes": [
        {
            "@id": "http://cnschema.org/Vehicle", 
            "_last": true, 
            "rdfs:label": "Vehicle"
        }
    ], 
    "nameZh": "车辆特殊用途", 
    "rangeIncludes": [
        {
            "@id": "http://cnschema.org/Text", 
            "_last": true, 
            "rdfs:label": "Text"
        }
    ], 
    "rdfs:comment": "Indicates whether the vehicle has been used for special purposes, like commercial rental, driving school, or as a taxi. The legislation in many countries requires this information to be revealed when offering a car for sale.", 
    "rdfs:label": "vehicleSpecialUsage", 
    "wikidataName": "", 
    "wikidataUrl": "", 
    "wikipediaUrl": ""
}